drt_sdk_network_providers/__init__.py
drt_sdk_network_providers/accounts.py
drt_sdk_network_providers/api_network_provider.py
drt_sdk_network_providers/api_network_provider_test.py
drt_sdk_network_providers/config.py
drt_sdk_network_providers/constants.py
drt_sdk_network_providers/contract_query_requests.py
drt_sdk_network_providers/contract_query_response.py
drt_sdk_network_providers/contract_results.py
drt_sdk_network_providers/errors.py
drt_sdk_network_providers/interface.py
drt_sdk_network_providers/network_config.py
drt_sdk_network_providers/network_general_statistics.py
drt_sdk_network_providers/network_stake.py
drt_sdk_network_providers/network_status.py
drt_sdk_network_providers/proxy_network_provider.py
drt_sdk_network_providers/proxy_network_provider_test.py
drt_sdk_network_providers/resources.py
drt_sdk_network_providers/token_definitions.py
drt_sdk_network_providers/tokens.py
drt_sdk_network_providers/transaction_events.py
drt_sdk_network_providers/transaction_logs.py
drt_sdk_network_providers/transaction_receipt.py
drt_sdk_network_providers/transaction_status.py
drt_sdk_network_providers/transactions.py
drt_sdk_network_providers/utils.py
drt_sdk_network_providers-0.0.1.dist-info/METADATA
drt_sdk_network_providers-0.0.1.dist-info/WHEEL
drt_sdk_network_providers-0.0.1.dist-info/licenses/LICENSE
drt_sdk_network_providers-0.0.1.dist-info/RECORD
