Metadata-Version: 2.3
Name: drt-sdk-network-providers
Version: 0.0.1
Summary: Network providers for Dharitri Python SDK.
Project-URL: Homepage, https://github.com/DharitriOne/drt-sdk-py-network-providers
Author: Dharitri
License-Expression: MIT
License-File: LICENSE
Classifier: License :: OSI Approved :: MIT License
Classifier: Operating System :: OS Independent
Classifier: Programming Language :: Python :: 3
Requires-Python: >=3.8
Requires-Dist: drt-sdk-core<0.1.0,>=0.0.1
Requires-Dist: requests==2.31.0
